power_fsm.v
// power_fsm.v
// Power controller FSM with hysteresis + dwell timer (Option D - medical-grade)
// - Inputs:
//    clk         : system clock
//    rst_n       : active-low synchronous reset
//    ml_class_i  : 2-bit class from ML predictor (0=IDLE,1=LOW,2=MED,3=HIGH)
// - Outputs:
//    mode_o      : 2-bit current power mode (0..3 same encoding)
//    clk_sel_o   : 2-bit clock select (0:/8, 1:/4, 2:/2, 3:/1)
//    enable_ml_o : enable signal for ML accelerator (1 when mode >= MED)
//    vmode_o     : 2-bit simulated voltage mode (same as mode_o)

`timescale 1ns/1ps
module power_fsm #(
    parameter integer HYST_COUNT       = 4,        // consecutive samples required to accept a new ml_class
    parameter integer DWELL_CYCLES     = 50        // minimum cycles to remain in a mode before change
)(
    input  wire        clk,
    input  wire        rst_n,
    input  wire [1:0]  ml_class_i,
    output reg  [1:0]  mode_o,
    output reg  [1:0]  clk_sel_o,
    output reg         enable_ml_o,
    output reg  [1:0]  vmode_o
);

    // Local state encoding (same as mode)
    localparam IDLE = 2'd0;
    localparam LOW  = 2'd1;
    localparam MED  = 2'd2;
    localparam HIGH = 2'd3;

    // Sampled ml_class and hysteresis counter
    reg [1:0] sampled_ml;            // last sampled ml_class
    integer   hyst_count;

    // Dwell timer to enforce minimum stay in a mode
    integer   dwell_counter;

    // Candidate mode derived from stable ml_class
    reg [1:0] candidate_mode;

    // update sampled_ml + hysteresis (synchronous)
    always @(posedge clk) begin
        if (!rst_n) begin
            sampled_ml   <= IDLE;
            hyst_count   <= 0;
            candidate_mode <= IDLE;
        end else begin
            if (ml_class_i == sampled_ml) begin
                if (hyst_count < HYST_COUNT)
                    hyst_count <= hyst_count + 1;
            end else begin
                sampled_ml <= ml_class_i;
                hyst_count <= 1;
            end

            // Accept candidate only when hyst_count reached threshold
            if (hyst_count >= HYST_COUNT)
                candidate_mode <= sampled_ml;
        end
    end

    // FSM transitions with dwell timer
    always @(posedge clk) begin
        if (!rst_n) begin
            mode_o      <= IDLE;
            clk_sel_o   <= IDLE; // match encoding: /8,/4,/2,/1
            enable_ml_o <= 1'b0;
            vmode_o     <= IDLE;
            dwell_counter <= 0;
        end else begin
            // increment dwell counter (saturates to a large number)
            if (dwell_counter < DWELL_CYCLES + 2)
                dwell_counter <= dwell_counter + 1;

            // Only allow mode change if candidate differs and dwell time satisfied
            if (candidate_mode != mode_o && dwell_counter >= DWELL_CYCLES) begin
                // change mode to candidate
                mode_o <= candidate_mode;
                dwell_counter <= 0; // reset dwell on mode change
            end

            // outputs mapping
            clk_sel_o <= mode_o;   // simple mapping: same encoding => clk divider selection
            vmode_o   <= mode_o;   // simulated voltage mode

            // enable ML only in MED/HIGH (configurable)
            if (mode_o >= MED)
                enable_ml_o <= 1'b1;
            else
                enable_ml_o <= 1'b0;
        end
    end

endmodule

power_fsm_tb.v
`timescale 1ns/1ps
module power_fsm_tb;

    reg clk;
    reg rst_n;
    reg [1:0] ml_class_i;

    wire [1:0] mode_o;
    wire [1:0] clk_sel_o;
    wire enable_ml_o;
    wire [1:0] vmode_o;

    // Instantiate with small timers for simulation quickness
    power_fsm #(
        .HYST_COUNT(3),     // require 3 stable samples
        .DWELL_CYCLES(20)   // remain min 20 cycles in a mode
    ) dut (
        .clk(clk),
        .rst_n(rst_n),
        .ml_class_i(ml_class_i),
        .mode_o(mode_o),
        .clk_sel_o(clk_sel_o),
        .enable_ml_o(enable_ml_o),
        .vmode_o(vmode_o)
    );

    // clock
    initial clk = 0;
    always #5 clk = ~clk; // 100 MHz style (10ns period)

    initial begin
        $dumpfile("power_fsm.vcd");
        $dumpvars(0, power_fsm_tb);

        // reset
        rst_n = 0;
        ml_class_i = 2'd0;
        #30;
        rst_n = 1;
        #20;

        // Scenario sequence:
        // start idle for some time
        ml_class_i = 2'd0; #100;

        // noisy input: flicker between 0 and 1 -> should remain IDLE due to hysteresis/dwell
        ml_class_i = 2'd1; #10;
        ml_class_i = 2'd0; #10;
        ml_class_i = 2'd1; #10;
        ml_class_i = 2'd1; #10;
        ml_class_i = 2'd1; #100; // sustained -> transition to LOW

        // climb to MED (simulate brief noise then stable MED)
        ml_class_i = 2'd2; #10;
        ml_class_i = 2'd1; #10;
        ml_class_i = 2'd2; #10;
        ml_class_i = 2'd2; #100; // sustain -> transition to MED

        // immediate jump to HIGH, ensure hysteresis still required
        ml_class_i = 2'd3; #10;
        ml_class_i = 2'd3; #10;
        ml_class_i = 2'd3; #100; // sustain -> transition to HIGH

        // noise back to LOW but short -> should not drop due to dwell timer
        ml_class_i = 2'd1; #30; // short
        ml_class_i = 2'd3; #100; // remain HIGH

        // allow time then force into IDLE
        ml_class_i = 2'd0; #200;

        $display("Test complete");
        $finish;
    end

    // display state changes
    reg [1:0] prev_mode;
    initial prev_mode = 2'bxx;
    always @(posedge clk) begin
        if (mode_o !== prev_mode) begin
            $display("[%0t] MODE_CHANGE: mode=%0d clk_sel=%0d enable_ml=%b vmode=%0d ml_in=%0d",
                     $time, mode_o, clk_sel_o, enable_ml_o, vmode_o, ml_class_i);
            prev_mode <= mode_o;
        end
    end

endmodule

power_fsm.vcd
$date
	Sat Nov 29 20:55:07 2025
$end
$version
	Icarus Verilog
$end
$timescale
	1ps
$end
$scope module power_fsm_tb $end
$var wire 2 ! vmode_o [1:0] $end
$var wire 2 " mode_o [1:0] $end
$var wire 1 # enable_ml_o $end
$var wire 2 $ clk_sel_o [1:0] $end
$var reg 1 % clk $end
$var reg 2 & ml_class_i [1:0] $end
$var reg 2 ' prev_mode [1:0] $end
$var reg 1 ( rst_n $end
$scope module dut $end
$var wire 1 % clk $end
$var wire 2 ) ml_class_i [1:0] $end
$var wire 1 ( rst_n $end
$var parameter 32 * DWELL_CYCLES $end
$var parameter 2 + HIGH $end
$var parameter 32 , HYST_COUNT $end
$var parameter 2 - IDLE $end
$var parameter 2 . LOW $end
$var parameter 2 / MED $end
$var reg 2 0 candidate_mode [1:0] $end
$var reg 2 1 clk_sel_o [1:0] $end
$var reg 1 # enable_ml_o $end
$var reg 2 2 mode_o [1:0] $end
$var reg 2 3 sampled_ml [1:0] $end
$var reg 2 4 vmode_o [1:0] $end
$var integer 32 5 dwell_counter [31:0] $end
$var integer 32 6 hyst_count [31:0] $end
$upscope $end
$upscope $end
$enddefinitions $end
$comment Show the parameter values. $end
$dumpall
b10 /
b1 .
b0 -
b11 ,
b11 +
b10100 *
$end
#0
$dumpvars
bx 6
bx 5
bx 4
bx 3
bx 2
bx 1
bx 0
b0 )
0(
bx '
b0 &
0%
bx $
x#
bx "
bx !
$end
#5000
b0 0
b0 6
b0 3
b0 5
b0 !
b0 4
0#
b0 $
b0 1
b0 "
b0 2
1%
#10000
0%
#15000
b0 '
1%
#20000
0%
#25000
1%
#30000
0%
1(
#35000
b1 5
b1 6
1%
#40000
0%
#45000
b10 6
b10 5
1%
#50000
0%
#55000
b11 5
b11 6
1%
#60000
0%
#65000
b100 5
1%
#70000
0%
#75000
b101 5
1%
#80000
0%
#85000
b110 5
1%
#90000
0%
#95000
b111 5
1%
#100000
0%
#105000
b1000 5
1%
#110000
0%
#115000
b1001 5
1%
#120000
0%
#125000
b1010 5
1%
#130000
0%
#135000
b1011 5
1%
#140000
0%
#145000
b1100 5
1%
#150000
0%
b1 &
b1 )
#155000
b1101 5
b1 6
b1 3
1%
#160000
0%
b0 &
b0 )
#165000
b0 3
b1110 5
1%
#170000
0%
b1 &
b1 )
#175000
b1111 5
b1 3
1%
#180000
0%
#185000
b10 6
b10000 5
1%
#190000
0%
#195000
b10001 5
b11 6
1%
#200000
0%
#205000
b1 0
b10010 5
1%
#210000
0%
#215000
b10011 5
1%
#220000
0%
#225000
b10100 5
1%
#230000
0%
#235000
b1 "
b1 2
b0 5
1%
#240000
0%
#245000
b1 !
b1 4
b1 $
b1 1
b1 5
b1 '
1%
#250000
0%
#255000
b10 5
1%
#260000
0%
#265000
b11 5
1%
#270000
0%
#275000
b100 5
1%
#280000
0%
#285000
b101 5
1%
#290000
0%
b10 &
b10 )
#295000
b110 5
b1 6
b10 3
1%
#300000
0%
b1 &
b1 )
#305000
b1 3
b111 5
1%
#310000
0%
b10 &
b10 )
#315000
b1000 5
b10 3
1%
#320000
0%
#325000
b10 6
b1001 5
1%
#330000
0%
#335000
b1010 5
b11 6
1%
#340000
0%
#345000
b10 0
b1011 5
1%
#350000
0%
#355000
b1100 5
1%
#360000
0%
#365000
b1101 5
1%
#370000
0%
#375000
b1110 5
1%
#380000
0%
#385000
b1111 5
1%
#390000
0%
#395000
b10000 5
1%
#400000
0%
#405000
b10001 5
1%
#410000
0%
#415000
b10010 5
1%
#420000
0%
b11 &
b11 )
#425000
b1 6
b11 3
b10011 5
1%
#430000
0%
#435000
b10100 5
b10 6
1%
#440000
0%
#445000
b11 6
b10 "
b10 2
b0 5
1%
#450000
0%
#455000
b10 '
1#
b10 !
b10 4
b10 $
b10 1
b1 5
b11 0
1%
#460000
0%
#465000
b10 5
1%
#470000
0%
#475000
b11 5
1%
#480000
0%
#485000
b100 5
1%
#490000
0%
#495000
b101 5
1%
#500000
0%
#505000
b110 5
1%
#510000
0%
#515000
b111 5
1%
#520000
0%
#525000
b1000 5
1%
#530000
0%
#535000
b1001 5
1%
#540000
0%
b1 &
b1 )
#545000
b1 6
b1 3
b1010 5
1%
#550000
0%
#555000
b1011 5
b10 6
1%
#560000
0%
#565000
b11 6
b1100 5
1%
#570000
0%
b11 &
b11 )
#575000
b1101 5
b1 0
b1 6
b11 3
1%
#580000
0%
#585000
b10 6
b1110 5
1%
#590000
0%
#595000
b1111 5
b11 6
1%
#600000
0%
#605000
b11 0
b10000 5
1%
#610000
0%
#615000
b10001 5
1%
#620000
0%
#625000
b10010 5
1%
#630000
0%
#635000
b10011 5
1%
#640000
0%
#645000
b10100 5
1%
#650000
0%
#655000
b11 "
b11 2
b0 5
1%
#660000
0%
#665000
b11 !
b11 4
b11 $
b11 1
b1 5
b11 '
1%
#670000
0%
b0 &
b0 )
#675000
b10 5
b1 6
b0 3
1%
#680000
0%
#685000
b10 6
b11 5
1%
#690000
0%
#695000
b100 5
b11 6
1%
#700000
0%
#705000
b0 0
b101 5
1%
#710000
0%
#715000
b110 5
1%
#720000
0%
#725000
b111 5
1%
#730000
0%
#735000
b1000 5
1%
#740000
0%
#745000
b1001 5
1%
#750000
0%
#755000
b1010 5
1%
#760000
0%
#765000
b1011 5
1%
#770000
0%
#775000
b1100 5
1%
#780000
0%
#785000
b1101 5
1%
#790000
0%
#795000
b1110 5
1%
#800000
0%
#805000
b1111 5
1%
#810000
0%
#815000
b10000 5
1%
#820000
0%
#825000
b10001 5
1%
#830000
0%
#835000
b10010 5
1%
#840000
0%
#845000
b10011 5
1%
#850000
0%
#855000
b10100 5
1%
#860000
0%
#865000
b0 "
b0 2
b0 5
1%
